mpstop/__init__.py
mpstop/monitor.py
mpstop-0.1.3.dist-info/licenses/LICENSE
mpstop-0.1.3.dist-info/METADATA
mpstop-0.1.3.dist-info/WHEEL
mpstop-0.1.3.dist-info/entry_points.txt
mpstop-0.1.3.dist-info/top_level.txt
mpstop-0.1.3.dist-info/RECORD
