Metadata-Version: 2.4
Name: mpstop
Version: 0.1.3
Summary: Minimal Apple Silicon (MPS) system monitor, nvitop-like for Mac
Home-page: https://github.com/gokulkarthik/mpstop
Author: Gokul
License: MIT
Project-URL: Source, https://github.com/gokulkarthik/mpstop
Project-URL: Tracker, https://github.com/gokulkarthik/mpstop/issues
Requires-Python: >=3.8
License-File: LICENSE
Requires-Dist: psutil
Requires-Dist: torch
Dynamic: author
Dynamic: description
Dynamic: description-content-type
Dynamic: home-page
Dynamic: license
Dynamic: license-file
Dynamic: project-url
Dynamic: requires-dist
Dynamic: requires-python
Dynamic: summary
